idefix/__init__.py
idefix/cli.py
idefix/controller.py
idefix/errors.py
idefix/model.py
idefix/old.py
idefix/dao/__init__.py
idefix/dao/abstract_dao.py
idefix/dao/mysql.py
idfx/__init__.py
idfx/cli.py
idfx/controller.py
idfx/errors.py
idfx/model.py
idfx/old.py
idfx/dao/__init__.py
idfx/dao/abstract_dao.py
idfx/dao/mysql.py
idfx-0.5.4.dist-info/AUTHORS.rst
idfx-0.5.4.dist-info/LICENSE
idfx-0.5.4.dist-info/METADATA
idfx-0.5.4.dist-info/WHEEL
idfx-0.5.4.dist-info/entry_points.txt
idfx-0.5.4.dist-info/top_level.txt
idfx-0.5.4.dist-info/RECORD
