Metadata-Version: 2.1
Name: idfx
Version: 0.5.4
Summary: Manga chapter checker
Home-page: https://github.com/the01/python-idefix
Author: the01
Author-email: jungflor@gmail.com
License: MIT License
Keywords: idefix manga
Platform: UNKNOWN
Classifier: Development Status :: 4 - Beta
Classifier: Intended Audience :: Developers
Classifier: License :: OSI Approved :: MIT License
Classifier: Natural Language :: English
Classifier: Programming Language :: Python :: 2
Classifier: Programming Language :: Python :: 2.7
Requires-Dist: flotils (<0.5,>=0.3.5a0)
Requires-Dist: floscraper (<0.3,>=0.2.2)
Requires-Dist: pymysql (<0.8,>=0.7.11)
Requires-Dist: lxml (<5,>=4.1.1)
